Metadata-Version: 2.1
Name: multiclipboard
Version: 1.0.0
Summary: Saves and loads pices of text to the clipboard, via a database in a .db file
Home-page: UNKNOWN
Author: Dari Developer
Author-email: hernandezdarifrancisco@gmail.com
License: MIT
Project-URL: Documentation, https://github.com/DariHernandez/multiclipboard/blob/master/README.md
Project-URL: Funding, https://www.paypal.com/paypalme/FranciscoDari
Project-URL: Source, https://github.com/DariHernandez/multiclipboard
Keywords: clipboard,multiclipboard,multi-clipboard
Platform: UNKNOWN
Requires-Python: >=3.7
